BetterADBSync/SAOLogging.py
BetterADBSync/__init__.py
BetterADBSync/argparsing.py
BetterADBSync/FileSystems/Android.py
BetterADBSync/FileSystems/Base.py
BetterADBSync/FileSystems/Local.py
BetterADBSync/FileSystems/__init__.py
BetterADBSync-1.3.2.dist-info/LICENSE
BetterADBSync-1.3.2.dist-info/METADATA
BetterADBSync-1.3.2.dist-info/WHEEL
BetterADBSync-1.3.2.dist-info/entry_points.txt
BetterADBSync-1.3.2.dist-info/top_level.txt
BetterADBSync-1.3.2.dist-info/RECORD
