Metadata-Version: 2.1
Name: BetterADBSync
Version: 1.3.2
Summary: Better version of adb-sync for Python3
License: 
Project-URL: Homepage, https://github.com/jb2170/better-adb-sync/
License-File: LICENSE
